{
    "needsErrorInfo": false,
    "mobileBottomRow": 51,
    "widgetName": "erroPutVac",
    "dynamicPropertyPathList": [{"key": "isVisible"}],
    "iconSVG": "/static/media/icon.a55b701a2ae86aa2c6718ecb7b4083f0.svg",
    "displayName": "Text",
    "topRow": 48,
    "searchTags": [
        "typography",
        "paragraph",
        "label"
    ],
    "bottomRow": 52,
    "parentRowSpace": 10,
    "type": "TEXT_WIDGET",
    "hideCard": false,
    "mobileRightColumn": 62,
    "animateLoading": true,
    "overflow": "NONE",
    "fontFamily": "{{appsmith.theme.fontFamily.appFont}}",
    "parentColumnSpace": 11.90625,
    "dynamicTriggerPathList": [],
    "leftColumn": 1,
    "dynamicBindingPathList": [
        {"key": "truncateButtonColor"},
        {"key": "fontFamily"},
        {"key": "borderRadius"},
        {"key": "isVisible"}
    ],
    "shouldTruncate": false,
    "truncateButtonColor": "{{appsmith.theme.colors.primaryColor}}",
    "text": "",
    "key": "zud0v0ucgk",
    "isDeprecated": false,
    "rightColumn": 62,
    "thumbnailSVG": "/static/media/thumbnail.0c129b82c9b3e4cd4920563b289659ab.svg",
    "textAlign": "LEFT",
    "dynamicHeight": "AUTO_HEIGHT",
    "widgetId": "zhpwnrismw",
    "minWidth": 450,
    "isVisible": "{{\n(function() {\n\tconst texto = erroPutVac.text.trim();\n  if(texto === \"\"){\n\t\treturn false\n\t}\n\telse{\n\t\treturn true\n\t}\n})();\n}}",
    "fontStyle": "BOLD",
    "textColor": "#231F20",
    "version": 1,
    "parentId": "xzh4441uyy",
    "tags": [
        "Suggested",
        "Content"
    ],
    "isLoading": false,
    "renderMode": "CANVAS",
    "mobileTopRow": 47,
    "responsiveBehavior": "fill",
    "originalTopRow": 48,
    "borderRadius": "{{appsmith.theme.borderRadius.appBorderRadius}}",
    "mobileLeftColumn": 46,
    "maxDynamicHeight": 9000,
    "originalBottomRow": 52,
    "fontSize": "1rem",
    "minDynamicHeight": 4
}