{
  "gitSyncId": "664b91393d0ee46738b29c21_666887ef18c92d39a8ad3133",
  "id": "Prescrições_get_vacinas_aplicadas",
  "pluginId": "restapi-plugin",
  "pluginType": "API",
  "unpublishedAction": {
    "actionConfiguration": {
      "autoGeneratedHeaders": [],
      "body": "",
      "bodyFormData": [],
      "encodeParamsToggle": true,
      "formData": {
        "apiContentType": "none"
      },
      "headers": [
        {
          "key": "Authorization",
          "value": "Bearer {{appsmith.store.jwt}}"
        }
      ],
      "httpMethod": "GET",
      "httpVersion": "HTTP11",
      "paginationType": "NONE",
      "path": "{{appsmith.store.url}}/api/animal-vacinas",
      "pluginSpecifiedTemplates": [
        {
          "value": true
        }
      ],
      "queryParameters": [
        {
          "key": "filters[animal][id]",
          "value": "{{seletor_animal.selectedOptionValue}}"
        },
        {
          "key": "filters[aplicado]",
          "value": "true"
        },
        {
          "key": "fields[0]",
          "value": "data_proxima_aplicacao"
        },
        {
          "key": "fields[1]",
          "value": "lembrete_em_dias"
        },
        {
          "key": "fields[2]",
          "value": "data_aplicacao"
        },
        {
          "key": "fields[3]",
          "value": "dose_atual"
        },
        {
          "key": "fields[4]",
          "value": "doses_totais"
        },
        {
          "key": "fields[5]",
          "value": "intervalo_entre_doses"
        },
        {
          "key": "fields[6]",
          "value": "observacao"
        },
        {
          "key": "populate[nome_vacina][fields][0]",
          "value": "nome"
        },
        {
          "key": "populate[nome_vacina][populate][tipo_vacina][fields][0]",
          "value": "tipo"
        },
        {
          "key": "populate[animal][fields][0]",
          "value": "Nome"
        },
        {
          "key": "populate[foto_etiqueta][fields][0]",
          "value": "*"
        },
        {
          "key": "populate[aplicado_por][fields][0]",
          "value": "username"
        },
        {
          "key": "pagination[pageSize]",
          "value": "10"
        },
        {
          "key": "pagination[page]",
          "value": "{{vacinas_aplicadas.pageNo}}"
        }
      ],
      "timeoutInMillisecond": 10000
    },
    "confirmBeforeExecute": false,
    "datasource": {
      "isAutoGenerated": false,
      "name": "DEFAULT_REST_DATASOURCE",
      "pluginId": "restapi-plugin"
    },
    "dynamicBindingPathList": [
      {
        "key": "headers[0].value"
      },
      {
        "key": "path"
      },
      {
        "key": "queryParameters[0].value"
      },
      {
        "key": "queryParameters[15].value"
      }
    ],
    "executeOnLoad": true,
    "name": "get_vacinas_aplicadas",
    "pageId": "Prescrições",
    "userSetOnLoad": false
  }
}