{
  "gitSyncId": "66bcf7b3d5cff221687cd2ca_42d47715-471e-4ae9-a398-6ea927366f3d",
  "id": "Peso_JSObject1.myFun1",
  "pluginId": "js-plugin",
  "pluginType": "JS",
  "unpublishedAction": {
    "actionConfiguration": {
      "encodeParamsToggle": true,
      "jsArguments": [],
      "paginationType": "NONE",
      "timeoutInMillisecond": 10000
    },
    "clientSideExecution": true,
    "collectionId": "Peso_JSObject1",
    "confirmBeforeExecute": false,
    "datasource": {
      "isAutoGenerated": false,
      "name": "UNUSED_DATASOURCE",
      "pluginId": "js-plugin"
    },
    "dynamicBindingPathList": [
      {
        "key": "body"
      }
    ],
    "executeOnLoad": true,
    "fullyQualifiedName": "JSObject1.myFun1",
    "name": "myFun1",
    "pageId": "Peso",
    "userSetOnLoad": true
  }
}